apache_commons_validator_python/__init__.py
apache_commons_validator_python/arg_new.py
apache_commons_validator_python/digester-rules.xml
apache_commons_validator_python/field_new.py
apache_commons_validator_python/form_new.py
apache_commons_validator_python/form_set_factory_new.py
apache_commons_validator_python/form_set_new.py
apache_commons_validator_python/generic_type_validator_new.py
apache_commons_validator_python/generic_validator_new.py
apache_commons_validator_python/msg_new.py
apache_commons_validator_python/validator_action_new.py
apache_commons_validator_python/validator_exception_new.py
apache_commons_validator_python/validator_new.py
apache_commons_validator_python/validator_resources_new.py
apache_commons_validator_python/validator_result_new.py
apache_commons_validator_python/validator_results_new.py
apache_commons_validator_python/var_new.py
apache_commons_validator_python/routines/__init__.py
apache_commons_validator_python/routines/abstract_calendar_validator.py
apache_commons_validator_python/routines/abstract_format_validator.py
apache_commons_validator_python/routines/abstract_number_validator.py
apache_commons_validator_python/routines/big_decimal_validator.py
apache_commons_validator_python/routines/big_integer_validator.py
apache_commons_validator_python/routines/byte_validator.py
apache_commons_validator_python/routines/calendar_validator.py
apache_commons_validator_python/routines/code_validator.py
apache_commons_validator_python/routines/credit_card_validator.py
apache_commons_validator_python/routines/currency_validator.py
apache_commons_validator_python/routines/date_validator.py
apache_commons_validator_python/routines/domain_validator.py
apache_commons_validator_python/routines/double_validator.py
apache_commons_validator_python/routines/email_validator.py
apache_commons_validator_python/routines/float_validator.py
apache_commons_validator_python/routines/inet_address_validator.py
apache_commons_validator_python-0.0.12.dist-info/licenses/LICENSE
apache_commons_validator_python-0.0.12.dist-info/METADATA
apache_commons_validator_python-0.0.12.dist-info/WHEEL
apache_commons_validator_python-0.0.12.dist-info/top_level.txt
apache_commons_validator_python-0.0.12.dist-info/RECORD
