Metadata-Version: 2.4
Name: apache-commons-validator-python
Version: 0.0.12
Summary: A Python translation of Apache Commons Validator
Author-email: Alicia Chu <ac2872@cornell.edu>, Juji Lau <jal499@cornell.edu>, Sanjana Nandi <sn523@cornell.edu>, Jessica Breuhaus <jb2784@cornell.edu>
License: Apache-2.0
Project-URL: Homepage, https://github.coecis.cornell.edu/sn523/apache-commons-validator-python
Requires-Python: <3.13,>=3.12
License-File: LICENSE
Requires-Dist: babel==2.11.0
Requires-Dist: pycountry
Requires-Dist: dateparser
Requires-Dist: pytest>=7.0.0
Requires-Dist: black
Requires-Dist: pylint
Requires-Dist: pytest-mock
Requires-Dist: coverage
Requires-Dist: sphinx
Requires-Dist: sphinx_rtd_theme
Dynamic: license-file
